seekh_data_scraper/__init__.py
seekh_data_scraper/nobaproject_data_scraping/__init__.py
seekh_data_scraper/nobaproject_data_scraping/main.py
seekh_data_scraper/nobaproject_data_scraping/noba_config.py
seekh_data_scraper/nobaproject_data_scraping/scraper/__init__.py
seekh_data_scraper/nobaproject_data_scraping/scraper/content.py
seekh_data_scraper/nobaproject_data_scraping/scraper/keyterms.py
seekh_data_scraper/nobaproject_data_scraping/scraper/questions.py
seekh_data_scraper/nobaproject_data_scraping/scraper/url_scraper.py
seekh_data_scraper/openstax_data_scraping/__init__.py
seekh_data_scraper/openstax_data_scraping/main.py
seekh_data_scraper/openstax_data_scraping/openstax_config.py
seekh_data_scraper/openstax_data_scraping/scraper/__init__.py
seekh_data_scraper/openstax_data_scraping/scraper/content.py
seekh_data_scraper/openstax_data_scraping/scraper/keyterms.py
seekh_data_scraper/openstax_data_scraping/scraper/questions.py
seekh_data_scraper/openstax_data_scraping/scraper/summary.py
seekh_data_scraper/openstax_data_scraping/scraper/url_grouper.py
seekh_data_scraper/wikipedia_data_scraping/__init__.py
seekh_data_scraper/wikipedia_data_scraping/main.py
seekh_data_scraper/wikipedia_data_scraping/wikipedia_config.py
seekh_data_scraper/wikipedia_data_scraping/scraper/__init__.py
seekh_data_scraper/wikipedia_data_scraping/scraper/content.py
seekh_data_scraper-0.3.5.dist-info/METADATA
seekh_data_scraper-0.3.5.dist-info/WHEEL
seekh_data_scraper-0.3.5.dist-info/top_level.txt
seekh_data_scraper-0.3.5.dist-info/RECORD
