Metadata-Version: 2.1
Name: seekh-data-scraper
Version: 0.3.5
Summary: A package for scraping data from Noba Project, OpenStax, and Wikipedia
Author-email: Your Name <your.email@example.com>
Project-URL: Homepage, https://github.com/yourusername/data-scraping
Project-URL: Bug Tracker, https://github.com/yourusername/data-scraping/issues
Classifier: Programming Language :: Python :: 3
Classifier: Operating System :: OS Independent
Requires-Python: >=3.7
